<ColumnData>
  <ContentColumn>
    <Bvin>1</Bvin>
    <DisplayName>STORE: Homepage 1</DisplayName>
    <SystemColumn>true</SystemColumn>
    <Blocks>
      <ContentBlock>
        <Bvin>88083e0b-db69-4299-bee5-8593491b50ad</Bvin>
        <ControlName>Banner Ad</ControlName>
        <SortOrder>1</SortOrder>
        <ColumnId>1</ColumnId>
        <SerializedSettings>{"imageurl":"{{assets}}HomeBanner.jpg","alttext":"Find Incredible Deals Today","cssclass":"","cssid":"homehero","linkurl":"#"}</SerializedSettings>
        <Lists>{"Items":[]}</Lists>
      </ContentBlock>
    </Blocks>
  </ContentColumn>
  <ContentColumn>
    <Bvin>2</Bvin>
    <DisplayName>STORE: Homepage 2</DisplayName>
    <SystemColumn>true</SystemColumn>
    <Blocks>
      <ContentBlock>
        <Bvin>88206da7-b1bb-497c-b4e4-56158cae41ab</Bvin>
        <ControlName>Banner Ad</ControlName>
        <SortOrder>1</SortOrder>
        <ColumnId>2</ColumnId>
        <SerializedSettings>{"imageurl":"{{assets}}homead1.png","alttext":"Homepage Ad One","cssclass":"homebanner","cssid":"homead1","linkurl":"#"}</SerializedSettings>
        <Lists>{"Items":[]}</Lists>
      </ContentBlock>
      <ContentBlock>
        <Bvin>6a36e234-1c3b-4085-9730-8260e61971b1</Bvin>
        <ControlName>Banner Ad</ControlName>
        <SortOrder>2</SortOrder>
        <ColumnId>2</ColumnId>
        <SerializedSettings>{"imageurl":"{{assets}}homead2.png","alttext":"Homepage Ad Two","cssclass":"homebanner","cssid":"homead2","linkurl":"#"}</SerializedSettings>
        <Lists>{"Items":[]}</Lists>
      </ContentBlock>
      <ContentBlock>
        <Bvin>f0e36d10-8050-4dc9-a424-c8897bd4e78e</Bvin>
        <ControlName>Banner Ad</ControlName>
        <SortOrder>3</SortOrder>
        <ColumnId>2</ColumnId>
        <SerializedSettings>{"imageurl":"{{assets}}homead3.png","alttext":"Homepage Ad Three","cssclass":"homebanner","cssid":"homead3","linkurl":"#"}</SerializedSettings>
        <Lists>{"Items":[]}</Lists>
      </ContentBlock>
    </Blocks>
  </ContentColumn>
  <ContentColumn>
    <Bvin>3</Bvin>
    <DisplayName>STORE: Homepage 3</DisplayName>
    <SystemColumn>true</SystemColumn>
    <Blocks />
  </ContentColumn>
  <ContentColumn>
    <Bvin>4</Bvin>
    <DisplayName>STORE: Category Sidebar</DisplayName>
    <SystemColumn>true</SystemColumn>
    <Blocks>
      <ContentBlock>
        <Bvin>d8862c8f-f8c5-4539-9b82-4fdc74523d0f</Bvin>
        <ControlName>Category Menu</ControlName>
        <SortOrder>1</SortOrder>
        <ColumnId>4</ColumnId>
        <SerializedSettings>{"Title":"","CategoryMenuMode":"3","ShowProductCount":"0","ShowCategoryCount":"0","HomeLink":"1","MaximumDepth":"0"}</SerializedSettings>
        <Lists>{"Items":[]}</Lists>
      </ContentBlock>
    </Blocks>
  </ContentColumn>
  <ContentColumn>
    <Bvin>5</Bvin>
    <DisplayName>STORE: Product Sidebar</DisplayName>
    <SystemColumn>true</SystemColumn>
    <Blocks>
      <ContentBlock>
        <Bvin>f81f2027-b0f2-4b88-bf13-1fa8b9feebb9</Bvin>
        <ControlName>Category Menu</ControlName>
        <SortOrder>1</SortOrder>
        <ColumnId>5</ColumnId>
        <SerializedSettings>{"Title":"","CategoryMenuMode":"3","ShowProductCount":"0","ShowCategoryCount":"0","HomeLink":"1","MaximumDepth":"0"}</SerializedSettings>
        <Lists>{"Items":[]}</Lists>
      </ContentBlock>
    </Blocks>
  </ContentColumn>
  <ContentColumn>
    <Bvin>201</Bvin>
    <DisplayName>STORE: My Account Sidebar</DisplayName>
    <SystemColumn>true</SystemColumn>
    <Blocks />
  </ContentColumn>
  <ContentColumn>
    <Bvin>202</Bvin>
    <DisplayName>STORE: Customer Service Sidebar</DisplayName>
    <SystemColumn>true</SystemColumn>
    <Blocks />
  </ContentColumn>
  <ContentColumn>
    <Bvin>601</Bvin>
    <DisplayName>STORE: Checkout Sidebar</DisplayName>
    <SystemColumn>true</SystemColumn>
    <Blocks>
      <ContentBlock>
        <Bvin>78019757-16e8-4a42-af4f-2314d9815b1c</Bvin>
        <ControlName>Html</ControlName>
        <SortOrder>1</SortOrder>
        <ColumnId>601</ColumnId>
        <SerializedSettings>{"HtmlData":"\u003cdiv class=\"decoratedblock\"\u003e\u003cdiv class=\"padded\"\u003eIf you have any questions or concerns please contact us:\u003cbr /\u003e&amp;nbsp;\u003cbr /\u003e{{storeaddress}}\u003cbr /\u003e&amp;nbsp;\u003cbr /\u003eYour order is secure!\u003c/div\u003e\u003c/div\u003e","PreTransformHtmlData":"\u003cdiv class=\"decoratedblock\"\u003e\u003cdiv class=\"padded\"\u003eIf you have any questions or concerns please contact us:\u003cbr /\u003e&amp;nbsp;\u003cbr /\u003e{{storeaddress}}\u003cbr /\u003e&amp;nbsp;\u003cbr /\u003eYour order is secure!\u003c/div\u003e\u003c/div\u003e"}</SerializedSettings>
        <Lists>{"Items":[]}</Lists>
      </ContentBlock>
      <ContentBlock>
        <Bvin>7eed7107-721d-4ed1-ad7b-9eef1d62681a</Bvin>
        <ControlName>Side Menu</ControlName>
        <SortOrder>2</SortOrder>
        <ColumnId>601</ColumnId>
        <SerializedSettings>{"Title":"Policies"}</SerializedSettings>
        <Lists>{"Items":[{"Id":"d7ddd3a7-1468-4b43-9fb8-612b3de85460","ListName":"Links","Setting1":"Privacy Policy","Setting2":"/policies/privacy","Setting3":"0","Setting4":"Privacy Policy","Setting5":"popover","Setting6":"","Setting7":"","Setting8":"","Setting9":"","Setting10":"","SortOrder":1},{"Id":"b8c78db7-8ddc-4279-bb84-700d2802feb5","ListName":"Links","Setting1":"Terms and Conditions","Setting2":"/policies/terms","Setting3":"0","Setting4":"Terms and Conditions","Setting5":"popover","Setting6":"","Setting7":"","Setting8":"","Setting9":"","Setting10":"","SortOrder":2},{"Id":"e8185ca6-087f-4462-a4ef-bc13c144b716","ListName":"Links","Setting1":"Return Policy","Setting2":"/policies/returns","Setting3":"0","Setting4":"Return Policy","Setting5":"popover","Setting6":"","Setting7":"","Setting8":"","Setting9":"","Setting10":"","SortOrder":3}]}</Lists>
      </ContentBlock>
    </Blocks>
  </ContentColumn>
</ColumnData>